sklearndf/__init__.py
sklearndf/_sklearn_version.py
sklearndf/_sklearndf.py
sklearndf/_util.py
sklearndf/py.typed
sklearndf/classification/__init__.py
sklearndf/classification/_classification.py
sklearndf/classification/_classification_v0_22.py
sklearndf/classification/_classification_v0_23.py
sklearndf/classification/_classification_v1_0.py
sklearndf/classification/_classification_v1_5.py
sklearndf/classification/_classification_v1_6.py
sklearndf/classification/extra/__init__.py
sklearndf/classification/extra/_extra.py
sklearndf/classification/wrapper/__init__.py
sklearndf/classification/wrapper/_wrapper.py
sklearndf/clustering/__init__.py
sklearndf/clustering/_clustering.py
sklearndf/clustering/_clustering_v1_1.py
sklearndf/clustering/_clustering_v1_3.py
sklearndf/clustering/wrapper/__init__.py
sklearndf/clustering/wrapper/_wrapper.py
sklearndf/pipeline/__init__.py
sklearndf/pipeline/_learner_pipeline.py
sklearndf/pipeline/_pipeline.py
sklearndf/pipeline/wrapper/__init__.py
sklearndf/pipeline/wrapper/_wrapper.py
sklearndf/regression/__init__.py
sklearndf/regression/_regression.py
sklearndf/regression/_regression_v0_22.py
sklearndf/regression/_regression_v0_23.py
sklearndf/regression/_regression_v1_0.py
sklearndf/regression/extra/__init__.py
sklearndf/regression/extra/_extra.py
sklearndf/regression/wrapper/__init__.py
sklearndf/regression/wrapper/_wrapper.py
sklearndf/transformation/__init__.py
sklearndf/transformation/_transformation.py
sklearndf/transformation/_transformation_v0_22.py
sklearndf/transformation/_transformation_v0_24.py
sklearndf/transformation/_transformation_v1_0.py
sklearndf/transformation/_transformation_v1_1.py
sklearndf/transformation/_transformation_v1_3.py
sklearndf/transformation/extra/__init__.py
sklearndf/transformation/extra/_extra.py
sklearndf/transformation/extra/wrapper/__init__.py
sklearndf/transformation/extra/wrapper/_wrapper.py
sklearndf/transformation/wrapper/__init__.py
sklearndf/transformation/wrapper/_wrapper.py
sklearndf-2.4.2.dist-info/licenses/LICENSE
sklearndf-2.4.2.dist-info/WHEEL
sklearndf-2.4.2.dist-info/METADATA
sklearndf-2.4.2.dist-info/RECORD
