Metadata-Version: 2.4
Name: sklearndf
Version: 2.4.2
Summary: Data frame support and feature traceability for `scikit-learn`.
Home-page: https://github.com/BCG-X-Official/sklearndf
Author: Boston Consulting Group (BCG)
Requires-Python: >=3.9,<4a
License: Apache Software License v2.0
Classifier: Development Status :: 5 - Production/Stable
Classifier: Intended Audience :: Science/Research
Classifier: License :: OSI Approved :: Apache Software License
Classifier: Operating System :: MacOS
Classifier: Operating System :: Microsoft :: Windows
Classifier: Operating System :: POSIX :: Linux
Classifier: Operating System :: Unix
Classifier: Programming Language :: Python
Classifier: Programming Language :: Python :: 3
Classifier: Programming Language :: Python :: 3.10
Classifier: Programming Language :: Python :: 3.11
Classifier: Programming Language :: Python :: 3.12
Classifier: Programming Language :: Python :: 3.13
Classifier: Topic :: Scientific/Engineering
License-File: LICENSE
Requires-Dist: gamma-pytools  >=2.1,<4a
Requires-Dist: numpy          >=1.21,<3a
Requires-Dist: packaging      >=20
Requires-Dist: pandas         >=1
Requires-Dist: scikit-learn   >=1.3,<1.8a
Requires-Dist: scipy          ~=1.6
Requires-Dist: sphinx ~= 4.5 ; extra == "docs"
Requires-Dist: sphinx-autodoc-typehints ~= 1.19 ; extra == "docs"
Requires-Dist: pydata-sphinx-theme ~= 0.8.1 ; extra == "docs"
Requires-Dist: jinja2 ~= 2.11 ; extra == "docs"
Requires-Dist: nbsphinx ~= 0.8.9 ; extra == "docs"
Requires-Dist: jupyter == 1 ; extra == "docs"
Requires-Dist: docutils ~= 0.17 ; extra == "docs"
Requires-Dist: xlrd ~= 1.2 ; extra == "docs"
Requires-Dist: m2r ~= 0.2 ; extra == "docs"
Requires-Dist: pytest ~= 8.1 ; extra == "testing"
Requires-Dist: pytest-cov ~= 4.1 ; extra == "testing"
Requires-Dist: lightgbm >= 3 ; extra == "testing"
Requires-Dist: xgboost >= 1 ; extra == "testing"
Project-URL: Documentation, https://bcg-x-official.github.io/sklearndf/
Project-URL: Repository, https://github.com/BCG-X-Official/sklearndf
Provides-Extra: docs
Provides-Extra: testing
